fds/__init__.py
fds/sdk/__init__.py
fds/sdk/FixedIncomeAnalyticsBatcher/__init__.py
fds/sdk/FixedIncomeAnalyticsBatcher/api_client.py
fds/sdk/FixedIncomeAnalyticsBatcher/configuration.py
fds/sdk/FixedIncomeAnalyticsBatcher/exceptions.py
fds/sdk/FixedIncomeAnalyticsBatcher/model_utils.py
fds/sdk/FixedIncomeAnalyticsBatcher/rest.py
fds/sdk/FixedIncomeAnalyticsBatcher/api/__init__.py
fds/sdk/FixedIncomeAnalyticsBatcher/api/fiab_calculations_api.py
fds/sdk/FixedIncomeAnalyticsBatcher/apis/__init__.py
fds/sdk/FixedIncomeAnalyticsBatcher/model/__init__.py
fds/sdk/FixedIncomeAnalyticsBatcher/model/event_summary.py
fds/sdk/FixedIncomeAnalyticsBatcher/model/fiab_calculation_parameters.py
fds/sdk/FixedIncomeAnalyticsBatcher/model/fiab_calculation_status.py
fds/sdk/FixedIncomeAnalyticsBatcher/model/fiab_calculation_status_summary.py
fds/sdk/FixedIncomeAnalyticsBatcher/model/fiab_calculation_status_summary_root.py
fds/sdk/FixedIncomeAnalyticsBatcher/model/fiab_date_parameters.py
fds/sdk/FixedIncomeAnalyticsBatcher/model/fiab_identifier.py
fds/sdk/FixedIncomeAnalyticsBatcher/models/__init__.py
fds.sdk.FixedIncomeAnalyticsBatcher-0.21.15.dist-info/LICENSE
fds.sdk.FixedIncomeAnalyticsBatcher-0.21.15.dist-info/METADATA
fds.sdk.FixedIncomeAnalyticsBatcher-0.21.15.dist-info/WHEEL
fds.sdk.FixedIncomeAnalyticsBatcher-0.21.15.dist-info/top_level.txt
fds.sdk.FixedIncomeAnalyticsBatcher-0.21.15.dist-info/RECORD
